Metadata-Version: 2.1
Name: CONVERSOR-MOEDA-REAL
Version: 0.0.1
Summary: Converte numero em Contábil Real
Home-page: UNKNOWN
Author: Evaldo Junior
Author-email: evaldoazeredoc@gmail.com
License: UNKNOWN
Platform: UNKNOWN
Requires-Python: >=3.8
License-File: LICENSE
